tako.py
takoyaki/__init__.py
takoyaki/accounts.py
takoyaki/cli/__init__.py
takoyaki/main.py
takoyaki/sute/__init__.py
takoyaki/sute/client.py
takoyaki/sute/config.py
takoyaki/sute/exception.py
takoyaki/sute/function.py
takoyaki/sute/objects.py
takoyaki/sute/sute.py
takoyaki/tools.py
takoyaki-2.dist-info/entry_points.txt
takoyaki-2.dist-info/WHEEL
takoyaki-2.dist-info/METADATA
takoyaki-2.dist-info/RECORD
