Metadata-Version: 2.1
Name: takoyaki
Version: 2
Summary: Instant burner mail account creation and management script.
Home-page: https://github.com/kebablord/takoyaki
License: MIT
Keywords: burner,cli,mail,burnermail
Author: Junicchi
Author-email: junicchi@waifu.club
Requires-Python: >=3.6
Classifier: Environment :: Console
Classifier: License :: OSI Approved :: MIT License
Classifier: Programming Language :: Python :: 3
Classifier: Programming Language :: Python :: 3.10
Classifier: Programming Language :: Python :: 3.6
Classifier: Programming Language :: Python :: 3.7
Classifier: Programming Language :: Python :: 3.8
Classifier: Programming Language :: Python :: 3.9
Requires-Dist: argparse (>=1.4.0,<2.0.0)
Requires-Dist: bs4 (>=0.0.1,<0.0.2)
Requires-Dist: colorama (>=0.4.4,<0.5.0)
Requires-Dist: questionary (>=1.9.0,<2.0.0)
Requires-Dist: requests (>=2.25.1,<3.0.0)
Requires-Dist: typing (>=3.7.4,<4.0.0)
Project-URL: Repository, https://github.com/kebablord/takoyaki
